lifeomic_patient_ml_types/schemas.py
lifeomic_patient_ml_types-10.0.0.dist-info/WHEEL
lifeomic_patient_ml_types-10.0.0.dist-info/METADATA
lifeomic_patient_ml_types-10.0.0.dist-info/RECORD
