Metadata-Version: 2.1
Name: lifeomic-patient-ml-types
Version: 10.0.0
Summary: Shared types for the patient-ml-service repos.
License: UNLICENSED
Author: LifeOmic
Author-email: development@lifeomic.com
Requires-Python: >=3.9,<4.0
Classifier: License :: Other/Proprietary License
Classifier: Programming Language :: Python :: 3
Classifier: Programming Language :: Python :: 3.9
Classifier: Programming Language :: Python :: 3.10
Classifier: Programming Language :: Python :: 3.11
